{
  "_format": "hh-sol-cache-2",
  "files": {
    "/home/crispy/ReactRepo/my-dapp/contracts/StorageBoi.sol": {
      "lastModificationDate": 1639156897989,
      "contentHash": "d3edea845f0e5c7b2da59e23e9e59a8f",
      "sourceName": "contracts/StorageBoi.sol",
      "solcConfig": {
        "version": "0.8.9",
        "settings": {
          "optimizer": {
            "enabled": false,
            "runs": 200
          },
          "outputSelection": {
            "*": {
              "*": [
                "abi",
                "evm.bytecode",
                "evm.deployedBytecode",
                "evm.methodIdentifiers",
                "metadata"
              ],
              "": [
                "ast"
              ]
            }
          }
        }
      },
      "imports": [],
      "versionPragmas": [
        "^0.8.0"
      ],
      "artifacts": [
        "StorageBoi"
      ]
    }
  }
}
